mcp_trendminer_server/__init__.py
mcp_trendminer_server/__main__.py
mcp_trendminer_server/server.py
mcp_trendminer_server/settings.py
mcp_trendminer_server/setup.py
mcp_trendminer_server/auth/__init__.py
mcp_trendminer_server/auth/context.py
mcp_trendminer_server/auth/provider.py
mcp_trendminer_server/client/__init__.py
mcp_trendminer_server/client/cache.py
mcp_trendminer_server/patches/__init__.py
mcp_trendminer_server/patches/auto_recovery.py
mcp_trendminer_server/patches/mcp_session_manager.py
mcp_trendminer_server/utils/__init__.py
mcp_trendminer_server/utils/connectivity.py
mcp_trendminer_server/utils/logging.py
mcp_trendminer_server/vendor/__init__.py
mcp_trendminer_server/vendor/trendminer_interface/__init__.py
mcp_trendminer_server/vendor/trendminer_interface/_input.py
mcp_trendminer_server/vendor/trendminer_interface/client.py
mcp_trendminer_server/vendor/trendminer_interface/component_factory.py
mcp_trendminer_server/vendor/trendminer_interface/constants.py
mcp_trendminer_server/vendor/trendminer_interface/datasource.py
mcp_trendminer_server/vendor/trendminer_interface/download_center.py
mcp_trendminer_server/vendor/trendminer_interface/exceptions.py
mcp_trendminer_server/vendor/trendminer_interface/asset/__init__.py
mcp_trendminer_server/vendor/trendminer_interface/asset/access.py
mcp_trendminer_server/vendor/trendminer_interface/asset/asset.py
mcp_trendminer_server/vendor/trendminer_interface/asset/attribute.py
mcp_trendminer_server/vendor/trendminer_interface/asset/base.py
mcp_trendminer_server/vendor/trendminer_interface/asset/client.py
mcp_trendminer_server/vendor/trendminer_interface/asset/node_multifactory.py
mcp_trendminer_server/vendor/trendminer_interface/asset/framework/__init__.py
mcp_trendminer_server/vendor/trendminer_interface/asset/framework/framework.py
mcp_trendminer_server/vendor/trendminer_interface/asset/framework/status.py
mcp_trendminer_server/vendor/trendminer_interface/authentication/__init__.py
tm_mcp_server_preview-0.1.3.dist-info/METADATA
tm_mcp_server_preview-0.1.3.dist-info/WHEEL
tm_mcp_server_preview-0.1.3.dist-info/entry_points.txt
tm_mcp_server_preview-0.1.3.dist-info/top_level.txt
tm_mcp_server_preview-0.1.3.dist-info/RECORD
