Metadata-Version: 2.4
Name: tm-mcp-server-preview
Version: 0.1.3
Summary: TrendMiner MCP Server (Preview) - AI assistant integration for TrendMiner
License-Expression: MIT
Project-URL: Homepage, https://github.com/TrendMinerCS/sdk
Project-URL: Documentation, https://github.com/TrendMinerCS/sdk#readme
Project-URL: Repository, https://github.com/TrendMinerCS/sdk
Project-URL: Issues, https://github.com/TrendMinerCS/sdk/issues
Keywords: mcp,trendminer,ai,assistant,industrial,analytics
Classifier: Development Status :: 4 - Beta
Classifier: Intended Audience :: Developers
Classifier: Intended Audience :: Manufacturing
Classifier: Programming Language :: Python :: 3
Classifier: Programming Language :: Python :: 3.13
Classifier: Topic :: Scientific/Engineering
Classifier: Topic :: Software Development :: Libraries :: Python Modules
Classifier: Operating System :: OS Independent
Requires-Python: >=3.13
Requires-Dist: fastmcp>=2.14.0
Requires-Dist: pandas>=2.3.3
Requires-Dist: pandas-stubs~=2.3.3
Requires-Dist: python-dotenv>=1.2.1
Requires-Dist: cachetools<7.0,>=6.0
Requires-Dist: isodate<0.8.0,>=0.7.2
Requires-Dist: numpy<3.0,>=2.0
Requires-Dist: python-dateutil<3.0.0,>=2.9.0
Requires-Dist: pytz<2026.0,>=2023.2
Requires-Dist: requests<3.0.0,>=2.28.0
Requires-Dist: urllib3<3.0.0,>=1.0.0
Requires-Dist: fastapi>=0.115.0
Requires-Dist: starlette>=0.41.0
Requires-Dist: httpx>=0.28.1
Requires-Dist: pydantic>=2.10.4
Requires-Dist: pydantic-settings>=2.7.0
